nufi/__init__.py
nufi/sent_proc.py
sentproc-0.0.1.dist-info/METADATA
sentproc-0.0.1.dist-info/WHEEL
sentproc-0.0.1.dist-info/top_level.txt
sentproc-0.0.1.dist-info/RECORD
